[{"mission_area_id":1,"mission_area_name":"Educational Support","subcategories":[{"subcategory_id":14,"subcategory_name":"LBTGQ+"},{"subcategory_id":13,"subcategory_name":"Inequality"},{"subcategory_id":12,"subcategory_name":"Human Rights and Trafficking"},{"subcategory_id":11,"subcategory_name":"Peace"}]},{"mission_area_id":2,"mission_area_name":"Health and Wellness","subcategories":[{"subcategory_id":19,"subcategory_name":"Holistic Wellness"},{"subcategory_id":18,"subcategory_name":"Substance Abuse"},{"subcategory_id":17,"subcategory_name":"Mental Health"},{"subcategory_id":16,"subcategory_name":"Disability"},{"subcategory_id":15,"subcategory_name":"Inclusion, Diversity & Equity"}]},{"mission_area_id":3,"mission_area_name":"Economic Sufficiency","subcategories":[{"subcategory_id":3,"subcategory_name":"Poetry"},{"subcategory_id":5,"subcategory_name":"Music\/Dance"},{"subcategory_id":4,"subcategory_name":"Theatre"},{"subcategory_id":2,"subcategory_name":"STEAM"},{"subcategory_id":1,"subcategory_name":"Others"}]},{"mission_area_id":4,"mission_area_name":"Social Justice","subcategories":[{"subcategory_id":25,"subcategory_name":"Waste"},{"subcategory_id":24,"subcategory_name":"Early Childhood"},{"subcategory_id":23,"subcategory_name":"STEM Education"},{"subcategory_id":22,"subcategory_name":"Civic and Political Engagement"},{"subcategory_id":21,"subcategory_name":"Literacy"},{"subcategory_id":20,"subcategory_name":"Medical Services"}]},{"mission_area_id":5,"mission_area_name":"International Service","subcategories":[{"subcategory_id":29,"subcategory_name":"Clean Energy"},{"subcategory_id":28,"subcategory_name":"Wildlife\/Animal Welfare"},{"subcategory_id":27,"subcategory_name":"Clean Water\/Water Management"},{"subcategory_id":26,"subcategory_name":"Gardens"}]},{"mission_area_id":6,"mission_area_name":"Environmental Stewardship","subcategories":[{"subcategory_id":10,"subcategory_name":"Disadvantaged Populations"},{"subcategory_id":9,"subcategory_name":"Refugees"},{"subcategory_id":8,"subcategory_name":"International Business"},{"subcategory_id":7,"subcategory_name":"Citizenship"},{"subcategory_id":6,"subcategory_name":"Inter\/Trans-culture"}]}]